translate_by_country/__init__.py
translate_by_country/translate_by_country.py
translate_by_country-0.0.8.dist-info/METADATA
translate_by_country-0.0.8.dist-info/WHEEL
translate_by_country-0.0.8.dist-info/top_level.txt
translate_by_country-0.0.8.dist-info/RECORD
